.gitattributes
.gitignore
LICENSE
README.md
setup.cfg
setup.py
binary_reader/__init__.py
binary_reader/binary_reader.py
binary_reader.egg-info/PKG-INFO
binary_reader.egg-info/SOURCES.txt
binary_reader.egg-info/dependency_links.txt
binary_reader.egg-info/top_level.txt