Metadata-Version: 2.1
Name: binary-reader
Version: 1.4.3
Summary: A python module for basic binary file IO.
Home-page: https://github.com/SutandoTsukai181/PyBinaryReader
Author: SutandoTsukai181
Author-email: mosamaeldeeb@gmail.com
License: MIT
Download-URL: https://github.com/SutandoTsukai181/PyBinaryReader/archive/refs/tags/v1.4.3.tar.gz
Keywords: BINARY,IO,STRUCT
Platform: UNKNOWN
Classifier: Development Status :: 5 - Production/Stable
Classifier: Intended Audience :: Developers
Classifier: Topic :: Software Development :: Build Tools
Classifier: License :: OSI Approved :: MIT License
Classifier: Programming Language :: Python :: 3.5
Classifier: Programming Language :: Python :: 3.8
